<annotation>
	<folder></folder>
	<filename>00000619_png.rf.1eca65f53db47d9351a32f1a15879ef4.jpg</filename>
	<path>00000619_png.rf.1eca65f53db47d9351a32f1a15879ef4.jpg</path>
	<source>
		<database>roboflow.com</database>
	</source>
	<size>
		<width>720</width>
		<height>720</height>
		<depth>3</depth>
	</size>
	<segmented>0</segmented>
	<object>
		<name>pistol</name>
		<pose>Unspecified</pose>
		<truncated>0</truncated>
		<difficult>0</difficult>
		<occluded>0</occluded>
		<bndbox>
			<xmin>213</xmin>
			<xmax>256</xmax>
			<ymin>611</ymin>
			<ymax>648</ymax>
		</bndbox>
	</object>
</annotation>
