<annotation>
	<folder></folder>
	<filename>A3F1QvCHQLQ_30_60_000318_jpg.rf.977ac409409799eeb38276e30781e7b9.jpg</filename>
	<path>A3F1QvCHQLQ_30_60_000318_jpg.rf.977ac409409799eeb38276e30781e7b9.jpg</path>
	<source>
		<database>roboflow.com</database>
	</source>
	<size>
		<width>1280</width>
		<height>720</height>
		<depth>3</depth>
	</size>
	<segmented>0</segmented>
	<object>
		<name>pistol</name>
		<pose>Unspecified</pose>
		<truncated>0</truncated>
		<difficult>0</difficult>
		<occluded>0</occluded>
		<bndbox>
			<xmin>609</xmin>
			<xmax>1006</xmax>
			<ymin>2</ymin>
			<ymax>255</ymax>
		</bndbox>
	</object>
	<object>
		<name>pistol</name>
		<pose>Unspecified</pose>
		<truncated>0</truncated>
		<difficult>0</difficult>
		<occluded>0</occluded>
		<bndbox>
			<xmin>141</xmin>
			<xmax>1082</xmax>
			<ymin>71</ymin>
			<ymax>678</ymax>
		</bndbox>
	</object>
</annotation>
