<annotation>
	<folder></folder>
	<filename>A3F1QvCHQLQ_30_60_000088_jpg.rf.b80958e63d8135949a6c7181907ece4b.jpg</filename>
	<path>A3F1QvCHQLQ_30_60_000088_jpg.rf.b80958e63d8135949a6c7181907ece4b.jpg</path>
	<source>
		<database>roboflow.com</database>
	</source>
	<size>
		<width>1280</width>
		<height>720</height>
		<depth>3</depth>
	</size>
	<segmented>0</segmented>
	<object>
		<name>pistol</name>
		<pose>Unspecified</pose>
		<truncated>0</truncated>
		<difficult>0</difficult>
		<occluded>0</occluded>
		<bndbox>
			<xmin>2</xmin>
			<xmax>738</xmax>
			<ymin>2</ymin>
			<ymax>505</ymax>
		</bndbox>
	</object>
</annotation>
