<annotation>
	<folder>JPEGImages</folder>
	<filename>CAR01451.jpg</filename>
	<path>/media/pico-titanium/HDD1/data/EAAI_Test/VOC2007/JPEGImages/CAR01451.jpg</path>
	<source>
		<database>Unknown</database>
	</source>
	<size>
		<width>233</width>
		<height>431</height>
		<depth>3</depth>
	</size>
	<segmented>0</segmented>
	<object>
		<name>pistol</name>
		<pose>Unspecified</pose>
		<truncated>0</truncated>
		<difficult>0</difficult>
		<bndbox>
			<xmin>119</xmin>
			<ymin>106</ymin>
			<xmax>182</xmax>
			<ymax>174</ymax>
		</bndbox>
	</object>
</annotation>
