<annotation>
  <folder>Definitiva</folder>
  <filename>armas_2213.jpg</filename>
  <path>C:\Users\Rob\Desktop\Definitiva\armas (59).jpg</path>
  <source>
    <database>Unknown</database>
  </source>
  <size>
    <width>512</width>
    <height>512</height>
    <depth>3</depth>
  </size>
  <segmented>0</segmented>
  <object>
    <name>pistol</name>
    <pose>Unspecified</pose>
    <truncated>0</truncated>
    <difficult>0</difficult>
    <bndbox>
      <xmin>52</xmin>
      <ymin>58</ymin>
      <xmax>482</xmax>
      <ymax>456</ymax>
    </bndbox>
  </object>
</annotation>